eclipse_ecal-6.0.1.dist-info/METADATA
eclipse_ecal-6.0.1.dist-info/WHEEL
eclipse_ecal-6.0.1.dist-info/RECORD
eclipse_ecal-6.0.1.dist-info/licenses/NOTICE.md
eclipse_ecal-6.0.1.dist-info/licenses/LICENSE.txt
eclipse_ecal-6.0.1.dist-info/licenses/LICENSES/LICENSES_python_bindings/asio/LICENSE_1_0.txt
eclipse_ecal-6.0.1.dist-info/licenses/LICENSES/LICENSES_python_bindings/asio/COPYING
eclipse_ecal-6.0.1.dist-info/licenses/LICENSES/LICENSES_python_bindings/PcapPlusPlus/LICENSE
eclipse_ecal-6.0.1.dist-info/licenses/LICENSES/LICENSES_python_bindings/PcapPlusPlus/thirdparty/EndianPortable_license.txt
eclipse_ecal-6.0.1.dist-info/licenses/LICENSES/LICENSES_python_bindings/PcapPlusPlus/thirdparty/json_license.txt
eclipse_ecal-6.0.1.dist-info/licenses/LICENSES/LICENSES_python_bindings/PcapPlusPlus/thirdparty/MemPlumber_LICENSE.txt
eclipse_ecal-6.0.1.dist-info/licenses/LICENSES/LICENSES_python_bindings/PcapPlusPlus/thirdparty/LightPcapNg_LICENSE.txt
eclipse_ecal-6.0.1.dist-info/licenses/LICENSES/LICENSES_python_bindings/PcapPlusPlus/thirdparty/hash-library_LICENSE
eclipse_ecal-6.0.1.dist-info/licenses/LICENSES/LICENSES_python_bindings/PcapPlusPlus/thirdparty/Getopt-for-Visual-Studio_license.txt
eclipse_ecal-6.0.1.dist-info/licenses/LICENSES/LICENSES_python_bindings/Udpcap/LICENSE
eclipse_ecal-6.0.1.dist-info/licenses/LICENSES/LICENSES_python_bindings/yaml_cpp/LICENSE
eclipse_ecal-6.0.1.dist-info/licenses/LICENSES/LICENSES_python_bindings/nanobind/LICENSE
eclipse_ecal-6.0.1.dist-info/licenses/LICENSES/LICENSES_python_bindings/HDF5/COPYING
eclipse_ecal-6.0.1.dist-info/licenses/LICENSES/LICENSES_python_bindings/HDF5/COPYING_LBNL_HDF5
eclipse_ecal-6.0.1.dist-info/licenses/LICENSES/LICENSES_python_bindings/ecaludp/LICENSE
eclipse_ecal-6.0.1.dist-info/licenses/LICENSES/LICENSES_python_bindings/recycle/LICENSE.rst
eclipse_ecal-6.0.1.dist-info/licenses/LICENSES/LICENSES_python_bindings/tcp_pubsub/LICENSE
eclipse_ecal-6.0.1.dist-info/licenses/LICENSES/LICENSES_python_bindings/spdlog/LICENSE
eclipse_ecal-6.0.1.dist-info/licenses/LICENSES/LICENSES_python_bindings/robin_map/LICENSE
eclipse_ecal-6.0.1.dist-info/licenses/LICENSES/LICENSES_python_bindings/nanopb/LICENSE.txt
eclipse_ecal-6.0.1.dist-info/licenses/LICENSES/LICENSES_python_bindings/protobuf/LICENSE
eclipse_ecal-6.0.1.dist-info/licenses/LICENSES/LICENSES_python_bindings/eCAL/LICENSE.txt
ecal/libecal_core.so.6.0.1
ecal/_ecal_hdf5_py.cpython-310-x86_64-linux-gnu.so
ecal/nanobind_core.cpython-310-x86_64-linux-gnu.so
ecal/__init__.py
ecal/_ecal_core_py.cpython-310-x86_64-linux-gnu.so
ecal/libhdf5.so.310
ecal/libhdf5.so.310.3.0
ecal/libecal_core.so.6
ecal/core/__init__.py
ecal/core/service.py
ecal/core/core.py
ecal/core/publisher.py
ecal/core/subscriber.py
ecal/measurement/writer.py
ecal/measurement/__init__.py
ecal/measurement/measurement.py
ecal/measurement/hdf5.py
ecal/msg/__init__.py
ecal/msg/common/__init__.py
ecal/msg/common/core.py
ecal/msg/common/serializer.py
ecal/msg/string/__init__.py
ecal/msg/string/core.py
ecal/msg/string/serializer.py
ecal/msg/proto/helper.py
ecal/msg/proto/__init__.py
ecal/msg/proto/core.py
ecal/msg/proto/serializer.py
ecal/proto/helper.py
ecal/proto/__init__.py
