Metadata-Version: 2.4
Name: eclipse-ecal
Version: 6.0.1
Summary: High performance publish/subscribe middleware
Project-URL: Documentation, https://eclipse-ecal.github.io/ecal
Project-URL: Source, https://github.com/eclipse-ecal/ecal
Author-email: Eclipse eCAL Team <ecal-dev@eclipse.org>
License-Expression: Apache-2.0
License-File: LICENSE.txt
License-File: LICENSES/LICENSES_python_bindings/HDF5/COPYING
License-File: LICENSES/LICENSES_python_bindings/HDF5/COPYING_LBNL_HDF5
License-File: LICENSES/LICENSES_python_bindings/PcapPlusPlus/LICENSE
License-File: LICENSES/LICENSES_python_bindings/PcapPlusPlus/thirdparty/EndianPortable_license.txt
License-File: LICENSES/LICENSES_python_bindings/PcapPlusPlus/thirdparty/Getopt-for-Visual-Studio_license.txt
License-File: LICENSES/LICENSES_python_bindings/PcapPlusPlus/thirdparty/LightPcapNg_LICENSE.txt
License-File: LICENSES/LICENSES_python_bindings/PcapPlusPlus/thirdparty/MemPlumber_LICENSE.txt
License-File: LICENSES/LICENSES_python_bindings/PcapPlusPlus/thirdparty/hash-library_LICENSE
License-File: LICENSES/LICENSES_python_bindings/PcapPlusPlus/thirdparty/json_license.txt
License-File: LICENSES/LICENSES_python_bindings/Udpcap/LICENSE
License-File: LICENSES/LICENSES_python_bindings/asio/COPYING
License-File: LICENSES/LICENSES_python_bindings/asio/LICENSE_1_0.txt
License-File: LICENSES/LICENSES_python_bindings/eCAL/LICENSE.txt
License-File: LICENSES/LICENSES_python_bindings/ecaludp/LICENSE
License-File: LICENSES/LICENSES_python_bindings/nanobind/LICENSE
License-File: LICENSES/LICENSES_python_bindings/nanopb/LICENSE.txt
License-File: LICENSES/LICENSES_python_bindings/protobuf/LICENSE
License-File: LICENSES/LICENSES_python_bindings/recycle/LICENSE.rst
License-File: LICENSES/LICENSES_python_bindings/robin_map/LICENSE
License-File: LICENSES/LICENSES_python_bindings/spdlog/LICENSE
License-File: LICENSES/LICENSES_python_bindings/tcp_pubsub/LICENSE
License-File: LICENSES/LICENSES_python_bindings/yaml_cpp/LICENSE
License-File: NOTICE.md
Keywords: IPC,Middleware
Classifier: Topic :: Scientific/Engineering
Requires-Python: >=3.8
Requires-Dist: packaging
Requires-Dist: protobuf<7,>3.8
